{
  "projects": [
    {
      "id": "bed8",
      "name": "Desenvolvedor Junior",
      "budget": "1000",
      "category": {
        "id": "2",
        "name": "Desenvolvimento"
      },
      "cost": 0,
      "services": []
    },
    {
      "id": "399b",
      "name": "Desenvolvedor Pleno",
      "budget": "8000",
      "category": {
        "id": "2",
        "name": "Desenvolvimento"
      },
      "cost": 0,
      "services": []
    },
    {
      "id": "8611",
      "name": "Renato Souza do Nascimento",
      "budget": "20000",
      "category": {
        "id": "2",
        "name": "Desenvolvimento"
      },
      "cost": 0,
      "services": []
    },
    {
      "id": "efca",
      "name": "notion do erick",
      "budget": "13124124",
      "category": {
        "id": "4",
        "name": "Planejamento"
      },
      "cost": 0,
      "services": []
    },
    {
      "id": "ce22",
      "name": "Teste",
      "budget": "11111",
      "category": {
        "id": "2",
        "name": "Desenvolvimento"
      },
      "cost": 0,
      "services": []
    },
    {
      "id": "d38d",
      "name": "Curso Web Design (HTML, CSS, JS)",
      "budget": "500000",
      "category": {
        "id": "3",
        "name": "Design"
      },
      "cost": 0,
      "services": []
    },
    {
      "id": "e880",
      "name": "__rsouza_",
      "budget": "12",
      "category": {
        "id": "1",
        "name": "Infra"
      },
      "cost": 0,
      "services": []
    },
    {
      "id": "da50",
      "name": "Renato Souza do Nascimento",
      "budget": "13213",
      "category": {
        "id": "3",
        "name": "Design"
      },
      "cost": 0,
      "services": []
    }
  ],
  "categories": [
    {
      "id": "1",
      "name": "Infra"
    },
    {
      "id": "2",
      "name": "Desenvolvimento"
    },
    {
      "id": "3",
      "name": "Design"
    },
    {
      "id": "4",
      "name": "Planejamento"
    }
  ]
}